chimeera/__init__.py
chimeera/models.py
chimeera/urls.py
chimeera/views.py
chimeera/static/css/chimeera.css
chimeera/static/js/chimeera.js
chimeera/templates/chimeera/base.html
chimeera-0.1.0.dist-info/DESCRIPTION.rst
chimeera-0.1.0.dist-info/METADATA
chimeera-0.1.0.dist-info/RECORD
chimeera-0.1.0.dist-info/WHEEL
chimeera-0.1.0.dist-info/metadata.json
chimeera-0.1.0.dist-info/top_level.txt
